Metadata-Version: 2.4
Name: xhs-bailian-mcp-server-zhulong
Version: 0.1.0
Summary: Add your description here
Author-email: 修理匠 <zhanghuibin_83@163.com>
Requires-Python: >=3.10
Requires-Dist: bs4>=0.0.2
Requires-Dist: dashscope>=1.23.4
Requires-Dist: dotenv>=0.9.9
Requires-Dist: httpx>=0.28.1
Requires-Dist: mcp[cli]>=1.9.3
